{
  "project_info": {
    "project_number": "835413272517",
    "firebase_url": "https://image-picker-crop-compress.firebaseio.com",
    "project_id": "image-picker-crop-compress",
    "storage_bucket": "image-picker-crop-compress.appspot.com"
  },
  "client": [
    {
      "client_info": {
        "mobilesdk_app_id": "1:835413272517:android:224474fc2bc75ed5ef4dac",
        "android_client_info": {
          "package_name": "com.example.image_picker_crop_compress"
        }
      },
      "oauth_client": [
        {
          "client_id": "835413272517-hlfblqqokivh9o547l50eg3ck4n4t54i.apps.googleusercontent.com",
          "client_type": 3
        }
      ],
      "api_key": [
        {
          "current_key": "AIzaSyCRelw1S0KMb895ezL9NmYL58kwWbz3Vlc"
        }
      ],
      "services": {
        "appinvite_service": {
          "other_platform_oauth_client": [
            {
              "client_id": "835413272517-hlfblqqokivh9o547l50eg3ck4n4t54i.apps.googleusercontent.com",
              "client_type": 3
            }
          ]
        }
      }
    }
  ],
  "configuration_version": "1"
}